{"naive":{"median":17.9,"p90":61.0},"km":{"median":20.1,"p90":62.7},"censoredShare":0.095,"curves":[{"label":"전체","points":[[0.1,0.9999],[12.2,0.5929],[24.3,0.4572],[36.4,0.3164],[48.5,0.2132],[60.6,0.1161],[72.7,0.0468],[84.8,0.0241],[96.9,0.0143],[108.5,0.0093],[120.4,0.0072],[131.4,0.0066],[144.8,0.0062],[156.3,0.006],[178.5,0.0059],[922.6,0.0059],[935.9,0.0059],[946.9,0.0058],[989.2,0.0058],[1000.4,0.0057],[1027.9,0.0057],[1035.5,0.0056],[1056.0,0.0056],[1072.2,0.0056],[1084.8,0.0055],[1111.9,0.0055],[1132.3,0.0053],[1143.0,0.0053],[1157.8,0.0052],[1163.1,0.0052],[1181.5,0.0051],[1197.0,0.0051],[1214.3,0.005],[1233.9,0.0049],[1241.6,0.0049],[1254.8,0.0048],[1268.2,0.0047],[1290.7,0.0047],[1306.9,0.0046],[1316.0,0.0045],[1328.8,0.0043],[1354.9,0.0043],[1361.8,0.0041],[1379.0,0.0039],[1390.9,0.0034],[1403.2,0.0029],[1415.0,0.0027],[1421.6,0.0026],[1440.0,0.0002]]},{"label":"수동휠체어","points":[[0.1,0.9999],[12.2,0.6037],[24.3,0.4647],[36.4,0.3207],[48.5,0.215],[60.6,0.1136],[72.7,0.041],[84.8,0.019],[96.9,0.0105],[108.4,0.0069],[120.4,0.0048],[131.0,0.004],[144.8,0.0037],[156.3,0.0033],[178.5,0.0032],[922.6,0.0032],[935.9,0.0031],[989.2,0.003],[1111.9,0.003],[1131.4,0.0029],[1157.8,0.0028],[1181.5,0.0028],[1197.0,0.0027],[1233.9,0.0025],[1268.2,0.0024],[1315.7,0.0023],[1328.8,0.0022],[1357.5,0.0022],[1379.0,0.0019],[1386.7,0.0014],[1401.9,0.0013],[1440.0,0.0001]]},{"label":"전동휠체어","points":[[0.1,0.9996],[12.2,0.5794],[24.3,0.4425],[36.4,0.2953],[48.5,0.1919],[60.6,0.1013],[72.6,0.042],[84.7,0.0226],[96.2,0.0157],[108.5,0.0133],[118.7,0.0125],[131.4,0.0115],[139.4,0.011],[1000.4,0.0108],[1027.9,0.0106],[1033.2,0.0104],[1072.2,0.0102],[1110.9,0.01],[1132.3,0.0096],[1143.0,0.0092],[1214.3,0.009],[1241.6,0.0088],[1254.8,0.0084],[1290.7,0.0082],[1306.9,0.008],[1320.7,0.0078],[1344.0,0.0075],[1355.9,0.0073],[1401.6,0.0071],[1412.2,0.0067],[1440.0,0.0008]]}],"queue":[{"hour":0,"requests":65,"unassignedRate":0.0615,"p50Assign":1.7,"p90Assign":4.5,"p50Board":25.2,"p90Board":40.5},{"hour":1,"requests":52,"unassignedRate":0.0577,"p50Assign":0.9,"p90Assign":1.8,"p50Board":24.6,"p90Board":39.1},{"hour":2,"requests":29,"unassignedRate":0.0,"p50Assign":1.6,"p90Assign":3.1,"p50Board":27.2,"p90Board":38.5},{"hour":3,"requests":112,"unassignedRate":0.0536,"p50Assign":1.7,"p90Assign":25.7,"p50Board":30.1,"p90Board":43.8},{"hour":4,"requests":91,"unassignedRate":0.1868,"p50Assign":1.8,"p90Assign":23.7,"p50Board":23.1,"p90Board":35.8},{"hour":5,"requests":770,"unassignedRate":0.0636,"p50Assign":77.9,"p90Assign":103.6,"p50Board":18.6,"p90Board":31.7},{"hour":6,"requests":828,"unassignedRate":0.0978,"p50Assign":42.2,"p90Assign":60.3,"p50Board":25.2,"p90Board":41.9},{"hour":7,"requests":2709,"unassignedRate":0.1096,"p50Assign":45.2,"p90Assign":71.4,"p50Board":26.1,"p90Board":40.0},{"hour":8,"requests":2792,"unassignedRate":0.0888,"p50Assign":36.8,"p90Assign":59.0,"p50Board":23.9,"p90Board":37.6},{"hour":9,"requests":3365,"unassignedRate":0.0689,"p50Assign":12.2,"p90Assign":42.6,"p50Board":23.4,"p90Board":35.1},{"hour":10,"requests":3581,"unassignedRate":0.0539,"p50Assign":6.9,"p90Assign":31.4,"p50Board":21.8,"p90Board":32.2},{"hour":11,"requests":4795,"unassignedRate":0.1084,"p50Assign":31.3,"p90Assign":65.7,"p50Board":21.8,"p90Board":33.1},{"hour":12,"requests":3105,"unassignedRate":0.1201,"p50Assign":49.4,"p90Assign":66.8,"p50Board":22.7,"p90Board":34.8},{"hour":13,"requests":2348,"unassignedRate":0.0903,"p50Assign":20.9,"p90Assign":42.2,"p50Board":21.6,"p90Board":33.4},{"hour":14,"requests":3327,"unassignedRate":0.0424,"p50Assign":1.8,"p90Assign":15.5,"p50Board":19.5,"p90Board":29.8},{"hour":15,"requests":3866,"unassignedRate":0.0631,"p50Assign":7.1,"p90Assign":35.2,"p50Board":22.9,"p90Board":34.4},{"hour":16,"requests":2368,"unassignedRate":0.133,"p50Assign":12.2,"p90Assign":63.2,"p50Board":24.6,"p90Board":38.2},{"hour":17,"requests":1128,"unassignedRate":0.1995,"p50Assign":22.1,"p90Assign":82.2,"p50Board":25.6,"p90Board":38.7},{"hour":18,"requests":644,"unassignedRate":0.2205,"p50Assign":25.3,"p90Assign":61.4,"p50Board":23.0,"p90Board":34.6},{"hour":19,"requests":652,"unassignedRate":0.1365,"p50Assign":13.5,"p90Assign":44.7,"p50Board":21.8,"p90Board":32.3},{"hour":20,"requests":444,"unassignedRate":0.0991,"p50Assign":2.8,"p90Assign":33.0,"p50Board":18.8,"p90Board":31.1},{"hour":21,"requests":219,"unassignedRate":0.2648,"p50Assign":26.1,"p90Assign":55.9,"p50Board":28.5,"p90Board":45.7},{"hour":22,"requests":133,"unassignedRate":0.1654,"p50Assign":12.1,"p90Assign":45.4,"p50Board":28.0,"p90Board":46.5},{"hour":23,"requests":89,"unassignedRate":0.0562,"p50Assign":1.8,"p90Assign":34.6,"p50Board":25.2,"p90Board":40.1}],"fleet":[{"hour":0,"avgActive":2.2,"maxActive":5},{"hour":1,"avgActive":1.3,"maxActive":4},{"hour":2,"avgActive":0.8,"maxActive":4},{"hour":3,"avgActive":0.5,"maxActive":2},{"hour":4,"avgActive":2.7,"maxActive":5},{"hour":5,"avgActive":1.0,"maxActive":2},{"hour":6,"avgActive":0.0,"maxActive":0},{"hour":7,"avgActive":36.3,"maxActive":51},{"hour":8,"avgActive":46.1,"maxActive":64},{"hour":9,"avgActive":85.4,"maxActive":118},{"hour":10,"avgActive":83.6,"maxActive":111},{"hour":11,"avgActive":77.0,"maxActive":109},{"hour":12,"avgActive":63.7,"maxActive":86},{"hour":13,"avgActive":80.7,"maxActive":110},{"hour":14,"avgActive":81.1,"maxActive":130},{"hour":15,"avgActive":68.9,"maxActive":100},{"hour":16,"avgActive":66.1,"maxActive":94},{"hour":17,"avgActive":36.2,"maxActive":56},{"hour":18,"avgActive":23.9,"maxActive":37},{"hour":19,"avgActive":15.8,"maxActive":24},{"hour":20,"avgActive":16.1,"maxActive":26},{"hour":21,"avgActive":3.4,"maxActive":11},{"hour":22,"avgActive":4.4,"maxActive":5},{"hour":23,"avgActive":3.4,"maxActive":5}]}